graphtomation/__init__.py
graphtomation/crewai/__init__.py
graphtomation/crewai/client.py
graphtomation/crewai/executor.py
graphtomation/crewai/router.py
graphtomation/crewai/types.py
graphtomation/crewai/components/__init__.py
graphtomation/langgraph/__init__.py
graphtomation/langgraph/client.py
graphtomation/langgraph/executor.py
graphtomation/langgraph/router.py
graphtomation/langgraph/types.py
graphtomation/langgraph/components/__init__.py
graphtomation-0.2.0.dist-info/METADATA
graphtomation-0.2.0.dist-info/WHEEL
graphtomation-0.2.0.dist-info/top_level.txt
graphtomation-0.2.0.dist-info/RECORD
